{
  "project_name": "New DS Project",
  "project_slug": "{{ cookiecutter.project_name.lower().replace(' ', '_').replace('-', '_') }}",
  "description": "A short description of the project.",
  "author": "Jean Metz",
  "email": "jmetzz.dev@gmail.com",
  "github_username": "jmetzz",
  "version": "0.1.0",
  "copyright_year": "{% now 'utc', '%Y' %}",
  "license": [
    "MIT license",
    "BSD license",
    "BSD-3-Clause",
    "ISC license",
    "Apache Software License 2.0",
    "GNU General Public License v3",
    "Not open source",
    "No license file"
  ],
  "is_library": [
    true
  ],
  "__gh_slug": "{{ cookiecutter.github_username }}/{{ cookiecutter.project_slug }}"
}